mxos/__init__.py
mxos/mxos.py
mxos_cube3-0.1.2.dist-info/LICENSE
mxos_cube3-0.1.2.dist-info/METADATA
mxos_cube3-0.1.2.dist-info/WHEEL
mxos_cube3-0.1.2.dist-info/entry_points.txt
mxos_cube3-0.1.2.dist-info/top_level.txt
mxos_cube3-0.1.2.dist-info/RECORD
