Metadata-Version: 2.1
Name: mxos-cube3
Version: 0.1.2
Summary: MXCHIP MXOS command line tool for python3.  mxos-cube3 enables repositories version control, publishing and updating code from remotely hosted repositories, and invoking MXOS own build system and export functions, among other operations
Home-page: https://github.com/jams777/mxos-cube3
Author: jams777
Author-email: jams7777@gmail.com
License: UNKNOWN
Platform: UNKNOWN
Classifier: Programming Language :: Python :: 3
Classifier: License :: OSI Approved :: Apache Software License
Classifier: Operating System :: OS Independent
Requires-Python: >=3,<4
